oper_math_basic_project/__init__.py
oper_math_basic_project/resta.py
oper_math_basic_project/suma.py
oper_math_basic_project-0.0.1.dist-info/METADATA
oper_math_basic_project-0.0.1.dist-info/WHEEL
oper_math_basic_project-0.0.1.dist-info/top_level.txt
oper_math_basic_project-0.0.1.dist-info/RECORD
