Metadata-Version: 2.1
Name: oper-math-basic-project
Version: 0.0.1
Summary: A pacage with two basic math operations
Home-page: https://github.com/sabuat/package-operaciones.git
Author: Sabuat Urbina Ribeiro
Author-email: sabuaturbina@yahoo.com
Requires-Python: >=3.8
